setup.cfg
setup.py
xys/Devil.py
xys/__init__.py
xys.egg-info/PKG-INFO
xys.egg-info/SOURCES.txt
xys.egg-info/dependency_links.txt
xys.egg-info/top_level.txt