Metadata-Version: 2.2
Name: xys
Version: 1.4
Summary: Simple
Author: Nasr
Author-email: nasr2python@gmail.com
Classifier: Programming Language :: Python :: 3
Classifier: License :: OSI Approved :: MIT License
Classifier: Operating System :: OS Independent
Dynamic: author
Dynamic: author-email
Dynamic: classifier
Dynamic: summary
